eric7/__init__.py
eric7/__version__.py
eric7/eric7_server.py
eric7/DebugClients/__init__.py
eric7/DebugClients/Python/AsyncFile.py
eric7/DebugClients/Python/BreakpointWatch.py
eric7/DebugClients/Python/DebugBase.py
eric7/DebugClients/Python/DebugClient.py
eric7/DebugClients/Python/DebugClientBase.py
eric7/DebugClients/Python/DebugClientCapabilities.py
eric7/DebugClients/Python/DebugConfig.py
eric7/DebugClients/Python/DebugUtilities.py
eric7/DebugClients/Python/DebugVariables.py
eric7/DebugClients/Python/FlexCompleter.py
eric7/DebugClients/Python/ModuleLoader.py
eric7/DebugClients/Python/MultiProcessDebugExtension.py
eric7/DebugClients/Python/MultiprocessingExtension.py
eric7/DebugClients/Python/PyProfile.py
eric7/DebugClients/Python/QProcessExtension.py
eric7/DebugClients/Python/SubprocessExtension.py
eric7/DebugClients/Python/ThreadExtension.py
eric7/DebugClients/Python/__init__.py
eric7/DebugClients/Python/eric7dbgstub.py
eric7/DebugClients/Python/getpass.py
eric7/RemoteServer/EricRequestCategory.py
eric7/RemoteServer/EricServer.py
eric7/RemoteServer/EricServerBaseRequestHandler.py
eric7/RemoteServer/EricServerCoverageRequestHandler.py
eric7/RemoteServer/EricServerDebuggerRequestHandler.py
eric7/RemoteServer/EricServerEditorConfigRequestHandler.py
eric7/RemoteServer/EricServerFileSystemRequestHandler.py
eric7/RemoteServer/__init__.py
eric7/SystemUtilities/FileSystemUtilities.py
eric7/SystemUtilities/OSUtilities.py
eric7/SystemUtilities/__init__.py
eric_ide_server-24.12.dist-info/METADATA
eric_ide_server-24.12.dist-info/WHEEL
eric_ide_server-24.12.dist-info/entry_points.txt
eric_ide_server-24.12.dist-info/top_level.txt
eric_ide_server-24.12.dist-info/RECORD
