Metadata-Version: 2.1
Name: eric-ide-server
Version: 24.12
Summary: eric7_server is the server part of the eric7 IDE.
Author: Detlev Offenbach
Author-email: Detlev Offenbach <detlev@die-offenbachs.de>
Maintainer: Detlev Offenbach
Maintainer-email: Detlev Offenbach <detlev@die-offenbachs.de>
License: GPLv3
Project-URL: Homepage, https://eric-ide.python-projects.org
Project-URL: Donation, https://www.paypal.com/donate/?hosted_button_id=XG3RSPKE3YAJ2
Project-URL: Issues Tracker, https://tracker.die-offenbachs.homelinux.org/
Project-URL: Source Code, https://hg.die-offenbachs.homelinux.org/eric/
Project-URL: Download, https://sourceforge.net/projects/eric-ide/files/latest/download
Project-URL: Mailing List, https://www.riverbankcomputing.com/mailman/listinfo/eric
Project-URL: News, https://eric-ide.python-projects.org/eric-news.html
Keywords: Development,eric-ide,IDE,Python3
Platform: FreeBSD
Platform: Linux
Platform: macOS
Platform: Windows
Classifier: License :: OSI Approved :: GNU General Public License v3 (GPLv3)
Classifier: Development Status :: 5 - Production/Stable
Classifier: Environment :: Console
Classifier: Environment :: MacOS X
Classifier: Environment :: Win32 (MS Windows)
Classifier: Intended Audience :: Developers
Classifier: Intended Audience :: End Users/Desktop
Classifier: Operating System :: MacOS :: MacOS X
Classifier: Operating System :: Microsoft :: Windows :: Windows 10
Classifier: Operating System :: Microsoft :: Windows :: Windows 11
Classifier: Operating System :: POSIX :: BSD
Classifier: Operating System :: POSIX :: BSD :: FreeBSD
Classifier: Operating System :: POSIX :: Linux
Classifier: Programming Language :: Python
Classifier: Programming Language :: Python :: 3
Classifier: Programming Language :: Python :: 3.8
Classifier: Programming Language :: Python :: 3.9
Classifier: Programming Language :: Python :: 3.10
Classifier: Programming Language :: Python :: 3.11
Classifier: Programming Language :: Python :: 3.12
Classifier: Programming Language :: Python :: 3.13
Classifier: Programming Language :: Python :: Implementation :: CPython
Classifier: Topic :: Software Development
Classifier: Topic :: Software Development :: Debuggers
Classifier: Topic :: Text Editors :: Integrated Development Environments (IDE)
Requires-Python: <3.14,>=3.9
Requires-Dist: pip>=21.1
Requires-Dist: EditorConfig
Requires-Dist: coverage>=6.5.0
